textlog2json
