Metadata-Version: 1.0
Name: textlog2json
Version: 0.4
Summary: parses log messages
Home-page: UNKNOWN
Author: Gellweiler, Sebastian
Author-email: UNKNOWN
License: UNKNOWN
Platform: UNKNOWN
